{"backedUpAt":1782712315,"branch":"main","excludedDirectories":[],"repo":"https://github.com/Gavinzip/renaiss_bnb_soccer_data.git","source":"soccer","summary":{"dataDir":"soccer","ledger":{"exists":true,"generatedAt":1782712311,"ledgerHash":"0xa88412647bc53fd774e3917f1b4f71d434a8a827ddc87126d39943656466d0a2","totalBonusTickets":0,"totalEntries":306,"totalFinalTickets":25725,"totalRawTickets":25725},"votes":{"allocationCount":1,"eventCount":1,"exists":true,"generatedAt":"2026-06-18T12:58:27.932Z","updatedAt":"2026-06-23T15:10:31.797Z"}}}
