{"backedUpAt":1781980266,"branch":"main","excludedDirectories":[],"repo":"https://github.com/Gavinzip/renaiss_bnb_soccer_data.git","source":"soccer","summary":{"dataDir":"soccer","ledger":{"exists":true,"generatedAt":1781979864,"ledgerHash":"0x5125ee70a1159fe58b3e6b126de963723585f887773ce9bd3003caf641c24687","totalBonusTickets":7406,"totalEntries":170,"totalFinalTickets":19462,"totalRawTickets":12056},"votes":{"allocationCount":1,"eventCount":1,"exists":true,"generatedAt":"2026-06-18T12:58:27.932Z","updatedAt":"2026-06-18T12:58:27.933Z"}}}
