{"backedUpAt":1782627666,"branch":"main","excludedDirectories":[],"repo":"https://github.com/Gavinzip/renaiss_bnb_soccer_data.git","source":"soccer","summary":{"dataDir":"soccer","ledger":{"exists":true,"generatedAt":1782627662,"ledgerHash":"0x874b4fadfcbb77450de6c6b0d2fc39a7cb9d45502725009784305e930c44917d","totalBonusTickets":0,"totalEntries":273,"totalFinalTickets":21294,"totalRawTickets":21294},"votes":{"allocationCount":1,"eventCount":1,"exists":true,"generatedAt":"2026-06-18T12:58:27.932Z","updatedAt":"2026-06-23T15:10:31.797Z"}}}
