{"backedUpAt":1782672733,"branch":"main","excludedDirectories":[],"repo":"https://github.com/Gavinzip/renaiss_bnb_soccer_data.git","source":"soccer","summary":{"dataDir":"soccer","ledger":{"exists":true,"generatedAt":1782672730,"ledgerHash":"0xf9c356d1b58325de315b5a8847b3f58341c1cb43db02642274d157b3d654f85a","totalBonusTickets":0,"totalEntries":296,"totalFinalTickets":23592,"totalRawTickets":23592},"votes":{"allocationCount":1,"eventCount":1,"exists":true,"generatedAt":"2026-06-18T12:58:27.932Z","updatedAt":"2026-06-23T15:10:31.797Z"}}}
