{"backedUpAt":1782573145,"branch":"main","excludedDirectories":[],"repo":"https://github.com/Gavinzip/renaiss_bnb_soccer_data.git","source":"soccer","summary":{"dataDir":"soccer","ledger":{"exists":true,"generatedAt":1782573142,"ledgerHash":"0x50317dd60d850227d3aab125274548bcf27ca79e439b3abaa384a71073ce5252","totalBonusTickets":0,"totalEntries":265,"totalFinalTickets":21143,"totalRawTickets":21143},"votes":{"allocationCount":1,"eventCount":1,"exists":true,"generatedAt":"2026-06-18T12:58:27.932Z","updatedAt":"2026-06-23T15:10:31.797Z"}}}
