{"backedUpAt":1782521547,"branch":"main","excludedDirectories":[],"repo":"https://github.com/Gavinzip/renaiss_bnb_soccer_data.git","source":"soccer","summary":{"dataDir":"soccer","ledger":{"exists":true,"generatedAt":1782521543,"ledgerHash":"0x8ef34b6f46fffdbd608f7aad00691ca22aaa7568facdf15bd56a888be0e4a360","totalBonusTickets":0,"totalEntries":249,"totalFinalTickets":20023,"totalRawTickets":20023},"votes":{"allocationCount":1,"eventCount":1,"exists":true,"generatedAt":"2026-06-18T12:58:27.932Z","updatedAt":"2026-06-23T15:10:31.797Z"}}}
