{"backedUpAt":1781984881,"branch":"main","excludedDirectories":[],"repo":"https://github.com/Gavinzip/renaiss_bnb_soccer_data.git","source":"soccer","summary":{"dataDir":"soccer","ledger":{"exists":true,"generatedAt":1781984879,"ledgerHash":"0xbe148270b4a29235d0760c32983ecaf24b01dd7d1d6232a650bf04b14723deb7","totalBonusTickets":7422,"totalEntries":172,"totalFinalTickets":19559,"totalRawTickets":12137},"votes":{"allocationCount":1,"eventCount":1,"exists":true,"generatedAt":"2026-06-18T12:58:27.932Z","updatedAt":"2026-06-18T12:58:27.933Z"}}}
