{"backedUpAt":1781976667,"branch":"main","excludedDirectories":[],"repo":"https://github.com/Gavinzip/renaiss_bnb_soccer_data.git","source":"soccer","summary":{"dataDir":"soccer","ledger":{"exists":true,"generatedAt":1781976217,"ledgerHash":"0xc46898f7553f6892d7d980b51b08930e2c86ebb7fdf592b77f9326a4a7b7175a","totalBonusTickets":7136,"totalEntries":170,"totalFinalTickets":19012,"totalRawTickets":11876},"votes":{"allocationCount":1,"eventCount":1,"exists":true,"generatedAt":"2026-06-18T12:58:27.932Z","updatedAt":"2026-06-18T12:58:27.933Z"}}}
