{"backedUpAt":1782407913,"branch":"main","excludedDirectories":[],"repo":"https://github.com/Gavinzip/renaiss_bnb_soccer_data.git","source":"soccer","summary":{"dataDir":"soccer","ledger":{"exists":true,"generatedAt":1782407909,"ledgerHash":"0x1bf0cae8d0d95b58969bca0cab8ddf217d78a477a58e64458549ca9599c8f4d6","totalBonusTickets":11501,"totalEntries":217,"totalFinalTickets":28945,"totalRawTickets":17444},"votes":{"allocationCount":1,"eventCount":1,"exists":true,"generatedAt":"2026-06-18T12:58:27.932Z","updatedAt":"2026-06-23T15:10:31.797Z"}}}
