{"backedUpAt":1781807046,"branch":"main","excludedDirectories":[],"repo":"https://github.com/Gavinzip/renaiss_bnb_soccer_data.git","source":"soccer","summary":{"dataDir":"soccer","ledger":{"exists":true,"generatedAt":1781807045,"ledgerHash":"0x2f1e2a9657ccff5decc306b13841e9a5561cf0eac4b039cfdf7bb98b1fdf7705","totalBonusTickets":5261,"totalEntries":120,"totalFinalTickets":13860,"totalRawTickets":8599},"votes":{"allocationCount":1,"eventCount":1,"exists":true,"generatedAt":"2026-06-18T12:58:27.932Z","updatedAt":"2026-06-18T12:58:27.933Z"}}}
