{"backedUpAt":1781949783,"branch":"main","excludedDirectories":[],"repo":"https://github.com/Gavinzip/renaiss_bnb_soccer_data.git","source":"soccer","summary":{"dataDir":"soccer","ledger":{"exists":true,"generatedAt":1781949780,"ledgerHash":"0xd06d75055c651f3fbee4b8e6d7f8115bf8d4b8a5ab6a5c95f99d1b4bdbe825a0","totalBonusTickets":6835,"totalEntries":159,"totalFinalTickets":17921,"totalRawTickets":11086},"votes":{"allocationCount":1,"eventCount":1,"exists":true,"generatedAt":"2026-06-18T12:58:27.932Z","updatedAt":"2026-06-18T12:58:27.933Z"}}}
