{"backedUpAt":1782741092,"branch":"main","excludedDirectories":[],"repo":"https://github.com/Gavinzip/renaiss_bnb_soccer_data.git","source":"soccer","summary":{"dataDir":"soccer","ledger":{"exists":true,"generatedAt":1782741088,"ledgerHash":"0x532a4703c7451067997d8323b56d66c0c3a9dae600ea53b4b9e361766807e70b","totalBonusTickets":0,"totalEntries":328,"totalFinalTickets":26186,"totalRawTickets":26186},"votes":{"allocationCount":1,"eventCount":1,"exists":true,"generatedAt":"2026-06-18T12:58:27.932Z","updatedAt":"2026-06-23T15:10:31.797Z"}}}
