{
  "version": 1,
  "updatedAt": "2026-06-24T09:40:18.146Z",
  "oauth": {
    "KsSL1_RPjr3qNLYCa4e5Jgc6gAvFqNKGnaW1-9-Vq9c": {
      "provider": "renaiss",
      "codeVerifier": "aWlmUs--sImmmRjqwvwG08K8sLUUOvg4BVJa7HeB65E",
      "redirectUri": "https://renaiss-worldcup.zeabur.app/auth/callback",
      "nonce": "T5W1mq3z952oU6kkCTiDMA",
      "returnTo": "/?auth=error&reason=oauth_failed&provider=renaiss&stage=token_exchange",
      "connectSessionId": null,
      "createdAt": "2026-06-24T09:34:38.438Z",
      "expiresAt": "2026-06-24T09:44:38.438Z"
    },
    "jd3NLZJ4yM8AlmooOsYaXKA9VX-xQRsGEDR3lnQ3UCA": {
      "provider": "renaiss",
      "codeVerifier": "Wy_Mznm3-RbvNp6KVPI9fEIHTWm-tICLHeEq-8jDfY8",
      "redirectUri": "https://renaiss-worldcup.zeabur.app/auth/callback",
      "nonce": "_pZZmBLElPvptGrr10OK7g",
      "returnTo": "/",
      "connectSessionId": null,
      "createdAt": "2026-06-24T09:40:17.056Z",
      "expiresAt": "2026-06-24T09:50:17.056Z"
    },
    "S1T0zh1lw6uumYC9B96h0Voes0WSMecihFvY_fNDwL8": {
      "provider": "renaiss",
      "codeVerifier": "y6fwcoBnlt19UWFzqZGzNl9s-ayReZpjPaLfNCUO8A0",
      "redirectUri": "https://renaiss-worldcup.zeabur.app/auth/callback",
      "nonce": "Ik1TJrfI0aGDRbKL0SB81w",
      "returnTo": "/",
      "connectSessionId": null,
      "createdAt": "2026-06-24T09:40:18.146Z",
      "expiresAt": "2026-06-24T09:50:18.146Z"
    }
  },
  "wallet": {},
  "emailOtp": {}
}
