{
  "version": 1,
  "updatedAt": "2026-06-19T05:15:38.752Z",
  "sessions": {
    "de32a52696123b328d40f3f561307f367172c0feb9fe02810ddfbe9423174dbe": {
      "id": "de32a52696123b328d40f3f561307f367172c0feb9fe02810ddfbe9423174dbe",
      "createdAt": "2026-06-19T05:15:38.752Z",
      "updatedAt": "2026-06-19T05:15:38.752Z",
      "expiresAt": "2026-07-19T05:15:38.752Z",
      "identity": {
        "provider": "x",
        "providerUserId": "896396418994159617",
        "username": "treegavin0121",
        "name": "Gavin",
        "picture": "https://pbs.twimg.com/profile_images/2033588253132279809/8V1hIFIv_normal.jpg",
        "verified": false
      },
      "walletAddress": null,
      "resolver": {
        "status": "unresolved",
        "source": "identity-resolver",
        "walletAddress": null,
        "reason": "identity-resolver-not-configured"
      }
    }
  }
}
